.gitignore
.pre-commit-config.yaml
.readthedocs.yml
CITATION.cff
LICENSE
README.md
pyproject.toml
.github/dependabot.yml
.github/workflows/ci.yaml
.github/workflows/deploy_release.yaml
doc/.gitignore
doc/Makefile
doc/about.rst
doc/api.rst
doc/conf.py
doc/index.rst
doc/make.bat
doc/rtd_requirements.txt
sbmlmath/__init__.py
sbmlmath/cfunction.py
sbmlmath/csymbol.py
sbmlmath/mathml_parser.py
sbmlmath/mathml_printer.py
sbmlmath/species_symbol.py
sbmlmath.egg-info/PKG-INFO
sbmlmath.egg-info/SOURCES.txt
sbmlmath.egg-info/dependency_links.txt
sbmlmath.egg-info/requires.txt
sbmlmath.egg-info/top_level.txt
tests/test_csymbol.py
tests/test_mathml_parser_sbml_semantic_suite.py
tests/test_misc.py
tests/test_parser.py
tests/test_printer.py
tests/test_species_symbol.py