Metadata-Version: 2.4
Name: sbmlmath
Version: 0.4.1
Summary: SBML Math <-> SymPy
Author-email: Daniel Weindl <sci@danielweindl.de>
License-Expression: BSD-3-Clause
Project-URL: Homepage, https://github.com/dweindl/sbmlmath
Project-URL: Documentation, https://sbmlmath.readthedocs.io/
Project-URL: Repository, https://github.com/dweindl/sbmlmath.git
Project-URL: Bug Tracker, https://github.com/dweindl/sbmlmath/issues
Project-URL: PyPI, https://pypi.org/project/sbmlmath/
Requires-Python: >=3.9
License-File: LICENSE
Requires-Dist: python-libsbml>=5.20.4
Requires-Dist: sympy
Requires-Dist: pint
Requires-Dist: lxml>=4.6.4
Provides-Extra: test
Requires-Dist: pytest>=7; extra == "test"
Requires-Dist: pre-commit>=3; extra == "test"
Dynamic: license-file
